<?xml version="1.0" encoding="utf-8"?>
<metadata>
	<layout title="COM_REDEVENT_VENUEEVENTS_THUMB_LAYOUT">
		<message>
			<![CDATA[COM_REDEVENT_VENUEEVENTS_THUMB_LAYOUT_DESC]]>
		</message>
	</layout>

	<fields name="request" addfieldpath="/libraries/redevent/form/fields">
		<fieldset name="request" label="COM_REDEVENT_FIELDSET_LAYOUT_OPTIONS">
			<field name="id" type="revenuelist" label="COM_REDEVENT_Select_Venue" description="COM_REDEVENT_SELECTVENUE" />
		</fieldset>
		<fieldset name="params" label="COM_REDEVENT_FIELDSET_LAYOUT_OPTIONS">
			<field name="show_pagination" type="list"
				description="JGLOBAL_PAGINATION_DESC"
				label="JGLOBAL_PAGINATION_LABEL"
			>
				<option value="">JGLOBAL_USE_GLOBAL</option>
				<option value="0">JHIDE</option>
				<option value="1">JSHOW</option>
				<option value="2">JGLOBAL_AUTO</option>
			</field>

			<field name="show_pagination_results" type="list"
				label="JGLOBAL_PAGINATION_RESULTS_LABEL"
				description="JGLOBAL_PAGINATION_RESULTS_DESC">

				<option value="">JGLOBAL_USE_GLOBAL</option>
				<option value="0">JHIDE</option>
				<option value="1">JSHOW</option>
			</field>


			<field name="display_num" type="list" default="" label="COM_REDEVENT_EVENT_NUMBER"
				   description="COM_REDEVENT_EVENT_NUMBER_TIP">
				<option value="">JGLOBAL_USE_GLOBAL</option>
				<option value="5">5</option>
				<option value="10">10</option>
				<option value="15">15</option>
				<option value="20">20</option>
				<option value="25">25</option>
				<option value="30">30</option>
				<option value="50">50</option>
				<option value="100">100</option>
				<option value="200">200</option>
			</field>
		</fieldset>
	</fields>
</metadata>
