<?xml version="1.0" encoding="utf-8"?>
<metadata>
	<layout title="COM_REDEVENT_Venues_map_Layout">
		<message>
			<![CDATA[COM_REDEVENT_VENUESMAP_LAYOUT_DESC]]>
		</message>
	</layout>
	
	<fields name="params" addfieldpath="/administrator/components/com_redevent/models/fields">
   	<fieldset name="params" label="COM_REDEVENT_FIELDSET_LAYOUT_OPTIONS">
      <field name="introtext" type="textarea" default="" label="COM_REDEVENT_INTROTEXT_FIELD" rows="8" cols="30" description="COM_REDEVENT_INTROTEXT_FIELD_TIP"/>
      <field name="showintrotext" type="radio" default="0" label="COM_REDEVENT_DISPLAY_INTROTEXT" description="COM_REDEVENT_DISPLAY_INTROTEXT_TIP">
        <option value="0">COM_REDEVENT_Hide</option>
        <option value="1">COM_REDEVENT_Show</option>
      </field>
      <field name="show_cat_filter" type="radio" default="1" label="COM_REDEVENT_DISPLAY_CATEGORY_FILTER" description="COM_REDEVENT_DISPLAY_CATEGORY_FILTER_DESC">
        <option value="0">No</option>
        <option value="1">Yes</option>
      </field>
      <field name="show_vcat_filter" type="radio" default="1" label="COM_REDEVENT_DISPLAY_VENUE_CATEGORY_FILTER" description="COM_REDEVENT_DISPLAY_CATEGORY_FILTER_DESC">
        <option value="0">No</option>
        <option value="1">Yes</option>
      </field>
      <field name="show_custom_filters" type="radio" default="1" label="COM_REDEVENT_DISPLAY_CUSTOM_FIELDS_FILTER" description="COM_REDEVENT_DISPLAY_CUSTOM_FIELDS_FILTER_DESC">
        <option value="0">No</option>
        <option value="1">Yes</option>
      </field>
      <field name="show_empty_venues" type="radio" default="0" label="COM_REDEVENT_DISPLAY_EMPTY_VENUES" description="COM_REDEVENT_DISPLAY_EMPTY_VENUES_DESC">
        <option value="0">No</option>
        <option value="1">Yes</option>
      </field>
    </fieldset>
	</fields>
</metadata>